flake8_imports.py
flake8_imports-0.1.1.dist-info/DESCRIPTION.rst
flake8_imports-0.1.1.dist-info/METADATA
flake8_imports-0.1.1.dist-info/RECORD
flake8_imports-0.1.1.dist-info/WHEEL
flake8_imports-0.1.1.dist-info/entry_points.txt
flake8_imports-0.1.1.dist-info/metadata.json
flake8_imports-0.1.1.dist-info/top_level.txt
