Metadata-Version: 2.0
Name: flake8-imports
Version: 0.1.1
Summary: isort extension flake8
Home-page: https://gitlab.com/mvantellingen/flake8-imports
Author: Michael van Tellingen
Author-email: michaelvantellingen@gmail.com
License: MIT
Platform: UNKNOWN
Classifier: Framework :: Flake8
Classifier: Environment :: Console
Classifier: Intended Audience :: Developers
Classifier: License :: OSI Approved :: MIT License
Classifier: Programming Language :: Python
Classifier: Programming Language :: Python :: 2
Classifier: Programming Language :: Python :: 3
Classifier: Topic :: Software Development :: Libraries :: Python Modules
Classifier: Topic :: Software Development :: Quality Assurance
Requires-Dist: flake8 (>=3.0.0)
Requires-Dist: isort
